artistools/__init__.py
artistools/__main__.py
artistools/artistoolscompletions.sh
artistools/codecomparison.py
artistools/commands.py
artistools/configuration.py
artistools/constants.py
artistools/hesma_scripts.py
artistools/linefluxes.py
artistools/logfiles.py
artistools/macroatom.py
artistools/make_vpkt_input.py
artistools/matplotlibrc
artistools/misc.py
artistools/plotspherical.py
artistools/plottools.py
artistools/py.typed
artistools/radfield.py
artistools/rustext.cpython-314-aarch64-linux-gnu.so
artistools/rustext.pyi
artistools/stats.py
artistools/test_artistools.py
artistools/transitions.py
artistools/version.py
artistools/viewing_angles_visualization.py
artistools/writecomparisondata.py
artistools/atomic/__init__.py
artistools/atomic/_atomic_core.py
artistools/atomic/test_atomic.py
artistools/data/.gitignore
artistools/data/ElBiEn_2007.txt
artistools/data/__init__.py
artistools/data/alphadecays.txt
artistools/data/atomic_properties.txt
artistools/data/betaminusdecays.txt
artistools/data/betaminusdecays_orig.txt
artistools/data/binding_energies.txt
artistools/data/collion-AR1985.txt
artistools/data/collion-reference.txt
artistools/data/collion.txt
artistools/data/elements.csv
artistools/data/solar_r_abundance_pattern.txt
artistools/data/splitmetadata.py
artistools/data/filters/400.txt
artistools/data/filters/520.txt
artistools/data/filters/B.txt
artistools/data/filters/FUV.txt
artistools/data/filters/H.txt
artistools/data/filters/H_ab.txt
artistools/data/filters/I.txt
artistools/data/filters/J.txt
artistools/data/filters/J_ab.txt
artistools/data/filters/K.txt
artistools/data/filters/K_ab.txt
artistools/data/filters/NUV.txt
artistools/data/filters/R.txt
artistools/data/filters/U.txt
artistools/data/filters/V.txt
artistools/data/filters/gs.txt
artistools/data/filters/is.txt
artistools/data/filters/rs.txt
artistools/data/filters/us.txt
artistools/data/filters/uvm2.txt
artistools-2025.11.6.4.dist-info/METADATA
artistools-2025.11.6.4.dist-info/WHEEL
artistools-2025.11.6.4.dist-info/entry_points.txt
artistools-2025.11.6.4.dist-info/top_level.txt
artistools-2025.11.6.4.dist-info/RECORD
artistools-2025.11.6.4.dist-info/licenses/LICENSE.txt
