Metadata-Version: 2.4
Name: artistools
Version: 2025.11.6.4
Summary: Plotting and analysis tools for the ARTIS 3D radiative transfer code for supernovae and kilonovae.
Author-email: "Luke J. Shingles" <luke.shingles@gmail.com>, "Christine E. Collins" <c.collins@gsi.de>, Alexander Holas <alexander.holas@h-its.org>, Fionntan Callan <fcallan02@qub.ac.uk>, Stuart Sim <s.sim@qub.ac.uk>, Joshua Pollin <jpollin02@qub.ac.uk>, Gerrit Leck <g.leck@gsi.de>
License-Expression: MIT
Project-URL: Repository, https://www.github.com/artis-mcrt/artistools
Project-URL: Source, https://www.github.com/artis-mcrt/artistools
Classifier: Intended Audience :: Science/Research
Classifier: Programming Language :: Python :: 3.11
Classifier: Programming Language :: Python :: 3.12
Classifier: Programming Language :: Python :: 3.13
Classifier: Programming Language :: Python :: 3.14
Classifier: Programming Language :: Python :: Free Threading
Classifier: Programming Language :: Rust
Classifier: Topic :: Scientific/Engineering :: Astronomy
Classifier: Topic :: Scientific/Engineering :: Physics
Requires-Python: >=3.11
License-File: LICENSE.txt
Requires-Dist: argcomplete>=3.6.2
Requires-Dist: extinction>=0.4.7
Requires-Dist: matplotlib>=3.10.6
Requires-Dist: numpy>=2.3.3
Requires-Dist: pandas>=2.3.2
Requires-Dist: polars>=1.33.1
Requires-Dist: pyarrow>=21.0.0
Requires-Dist: pypdf>=6.0.0
Requires-Dist: pyyaml>=6.0.2
Requires-Dist: rich>=14.1.0
Requires-Dist: scipy>=1.16.0
Requires-Dist: tqdm>=4.67.1
Requires-Dist: typing_extensions>=4.14
Requires-Dist: zstandard>=0.23.0; python_version < "3.14"
Provides-Extra: extras
Requires-Dist: astropy>=7.0.1; extra == "extras"
Requires-Dist: george>=0.4.4; extra == "extras"
Requires-Dist: imageio>=2.37.0; extra == "extras"
Requires-Dist: plotly>=6.0.1; extra == "extras"
Requires-Dist: pynonthermal>=2025.4.8; extra == "extras"
Requires-Dist: pyvista>=0.45; extra == "extras"
Requires-Dist: tabulate>=0.9; extra == "extras"
Dynamic: license-file
